AUTHORS
LICENSE
MANIFEST.in
README.rst
setup.py
cmsplugin_gallery/__init__.py
cmsplugin_gallery/admin.py
cmsplugin_gallery/cms_plugins.py
cmsplugin_gallery/forms.py
cmsplugin_gallery/models.py
cmsplugin_gallery/settings.py
cmsplugin_gallery/utils.py
cmsplugin_gallery/locale/en/LC_MESSAGES/django.mo
cmsplugin_gallery/locale/en/LC_MESSAGES/django.po
cmsplugin_gallery/locale/pl/LC_MESSAGES/django.mo
cmsplugin_gallery/locale/pl/LC_MESSAGES/django.po
cmsplugin_gallery/locale/ru/LC_MESSAGES/django.mo
cmsplugin_gallery/locale/ru/LC_MESSAGES/django.po
cmsplugin_gallery/migrations/0001_initial.py
cmsplugin_gallery/migrations/0002_auto__add_field_galleryplugin_template.py
cmsplugin_gallery/migrations/0003_move_images_to_media_path.py
cmsplugin_gallery/migrations/0004_auto__add_field_image_src_new.py
cmsplugin_gallery/migrations/0005_migrate_to_filer.py
cmsplugin_gallery/migrations/0006_auto__del_field_image_src.py
cmsplugin_gallery/migrations/0007_rename_src_new_to_src.py
cmsplugin_gallery/migrations/__init__.py
cmsplugin_gallery/templates/cmsplugin_gallery/gallery.html
cmsplugin_gallery_filer.egg-info/PKG-INFO
cmsplugin_gallery_filer.egg-info/SOURCES.txt
cmsplugin_gallery_filer.egg-info/dependency_links.txt
cmsplugin_gallery_filer.egg-info/requires.txt
cmsplugin_gallery_filer.egg-info/top_level.txt