Metadata-Version: 1.1
Name: cmsplugin-gallery-filer
Version: 0.5.2.1
Summary: DjangoCMS image gallery plugin with drag&drop reordering in admin, support for thumbnails and jQueryTOOLS overlay. Fork to use django-filer
Home-page: http://lagunak.gisa-elkartea.org/projects/cmsplugin-gallery-filer
Author: GISA Elkartea
Author-email: kontaktua@gisa-elkartea.org
License: UNKNOWN
Platform: UNKNOWN
Provides: cmsplugin_gallery
